rqpattr/__init__.py
rqpattr/_version.py
rqpattr/api.py
rqpattr/const.py
rqpattr/exceptions.py
rqpattr/logger.py
rqpattr/types.py
rqpattr/analysis/__init__.py
rqpattr/analysis/allocation_selection.cpython-310-x86_64-linux-gnu.so
rqpattr/analysis/benchmark.cpython-310-x86_64-linux-gnu.so
rqpattr/analysis/cache.cpython-310-x86_64-linux-gnu.so
rqpattr/analysis/classification.cpython-310-x86_64-linux-gnu.so
rqpattr/analysis/context.cpython-310-x86_64-linux-gnu.so
rqpattr/analysis/credit_score.cpython-310-x86_64-linux-gnu.so
rqpattr/analysis/linking.cpython-310-x86_64-linux-gnu.so
rqpattr/analysis/portfolio_performance.cpython-310-x86_64-linux-gnu.so
rqpattr/analysis/return_decomposition.cpython-310-x86_64-linux-gnu.so
rqpattr/analysis/bond_factor/__init__.py
rqpattr/analysis/bond_factor/analysis.cpython-310-x86_64-linux-gnu.so
rqpattr/analysis/bond_factor/attribution.cpython-310-x86_64-linux-gnu.so
rqpattr/analysis/bond_factor/convertible.cpython-310-x86_64-linux-gnu.so
rqpattr/analysis/brinson/__init__.py
rqpattr/analysis/brinson/analysis.cpython-310-x86_64-linux-gnu.so
rqpattr/analysis/brinson/brinson.cpython-310-x86_64-linux-gnu.so
rqpattr/analysis/brinson/index_cache.cpython-310-x86_64-linux-gnu.so
rqpattr/analysis/campisi/__init__.py
rqpattr/analysis/campisi/analysis.cpython-310-x86_64-linux-gnu.so
rqpattr/analysis/campisi/campisi.cpython-310-x86_64-linux-gnu.so
rqpattr/analysis/campisi/index_cache.cpython-310-x86_64-linux-gnu.so
rqpattr/analysis/hedging/__init__.py
rqpattr/analysis/hedging/analysis.cpython-310-x86_64-linux-gnu.so
rqpattr/analysis/hedging/drilldown.cpython-310-x86_64-linux-gnu.so
rqpattr/analysis/hedging/hedging.cpython-310-x86_64-linux-gnu.so
rqpattr/analysis/stock_factor/__init__.py
rqpattr/analysis/stock_factor/analysis.cpython-310-x86_64-linux-gnu.so
rqpattr/analysis/stock_factor/const.cpython-310-x86_64-linux-gnu.so
rqpattr/analysis/stock_factor/factor_based.cpython-310-x86_64-linux-gnu.so
rqpattr-0.0.35.dist-info/METADATA
rqpattr-0.0.35.dist-info/WHEEL
rqpattr-0.0.35.dist-info/top_level.txt
rqpattr-0.0.35.dist-info/RECORD
